LICENSE.txt
MANIFEST.in
README.rst
setup.cfg
setup.py
api/__init__.py
api/unfollower.py
unfollower.egg-info/PKG-INFO
unfollower.egg-info/SOURCES.txt
unfollower.egg-info/dependency_links.txt
unfollower.egg-info/entry_points.txt
unfollower.egg-info/requires.txt
unfollower.egg-info/top_level.txt
utils/__init__.py
utils/auth.py