Metadata-Version: 1.1
Name: unfollower
Version: 1.1.0
Summary: Unfollow all your twitter/instagram/facebook/etc. followers
Home-page: https://github.com/4thel00z/unfollower
Author: ransomware
Author-email: 4thel00z@gmail.com
License: License :: OSI Approved :: GNU Affero General Public License v3 or later (AGPLv3+)
Keywords: terminal social media twitter facebook unfollow
Platform: UNKNOWN
Classifier: Development Status :: 3 - Alpha
Classifier: Intended Audience :: Developers
Classifier: Topic :: Software Development :: Build Tools
Classifier: License :: OSI Approved :: GNU Affero General Public License v3 or later (AGPLv3+)
Classifier: Programming Language :: Python :: 2
Classifier: Programming Language :: Python :: 2.6
Classifier: Programming Language :: Python :: 2.7
Classifier: Programming Language :: Python :: 3
Classifier: Programming Language :: Python :: 3.3
Classifier: Programming Language :: Python :: 3.4
Classifier: Programming Language :: Python :: 3.5
